W3Alexandria/W3Alexandria.py
W3Alexandria/__init__.py
W3Alexandria/book.abi
W3Alexandria/book.bin
W3Alexandria/book_ipfs.abi
W3Alexandria/book_ipfs.bin
W3Alexandria/library.abi
W3Alexandria/library.bin
W3Alexandria-1.0.8.dist-info/LICENSE
W3Alexandria-1.0.8.dist-info/METADATA
W3Alexandria-1.0.8.dist-info/WHEEL
W3Alexandria-1.0.8.dist-info/top_level.txt
W3Alexandria-1.0.8.dist-info/RECORD
