Metadata-Version: 2.1
Name: W3Alexandria
Version: 1.0.8
Summary: A project to decentralize and distribute literary infrastructure.
Home-page: https://github.com/ObiajuluM/Alexandria
Author: Obiajulu_M
Author-email: oambanefo@outlook.com
License: MIT
Classifier: Programming Language :: Python :: 3
Classifier: License :: OSI Approved :: MIT License
Classifier: Operating System :: OS Independent
Requires-Python: >=3.8
License-File: LICENSE
Requires-Dist: web3
Requires-Dist: ipfshttpclient
